cscPy/__init__.py
cscPy-0.0.4.dist-info/LICENSE
cscPy-0.0.4.dist-info/METADATA
cscPy-0.0.4.dist-info/WHEEL
cscPy-0.0.4.dist-info/top_level.txt
cscPy-0.0.4.dist-info/RECORD
