Metadata-Version: 2.1
Name: cscPy
Version: 0.0.4
Summary: my personal library
Home-page: http://github.com/ShichengChen
Author: csc
Author-email: csc@example.com
License: MIT
License-File: LICENSE
